newssurvey/__init__.py
newssurvey/__main__.py
newssurvey/config.py
newssurvey/exceptions.py
newssurvey/newssurvey.py
newssurvey/types.py
newssurvey/prompts/0. common.txt
newssurvey/prompts/1.1. list_search_terms.txt
newssurvey/prompts/1.2. accumulate_search_terms.txt
newssurvey/prompts/2. filter_search_results.txt
newssurvey/prompts/3.1. list_sections.txt
newssurvey/prompts/3.2. refine_sections.txt
newssurvey/prompts/4. rate_article.txt
newssurvey/prompts/5. condense_article.txt
newssurvey/prompts/6. filter_articles.txt
newssurvey/prompts/7. combine_articles.txt
newssurvey/prompts/8. create_title.txt
newssurvey/prompts/disclaimer.txt
newssurvey/sources/medicalxpress/__init__.py
newssurvey/sources/medicalxpress/_common.py
newssurvey/sources/medicalxpress/article.py
newssurvey/sources/medicalxpress/search.py
newssurvey/sources/physorg/__init__.py
newssurvey/sources/physorg/_common.py
newssurvey/sources/physorg/article.py
newssurvey/sources/physorg/search.py
newssurvey/util/dict.py
newssurvey/util/difflib_.py
newssurvey/util/diskcache_.py
newssurvey/util/dotenv_.py
newssurvey/util/input.py
newssurvey/util/int.py
newssurvey/util/itertools_.py
newssurvey/util/openai_.py
newssurvey/util/scipy_.py
newssurvey/util/str.py
newssurvey/util/sys_.py
newssurvey/util/textwrap.py
newssurvey/util/threading_.py
newssurvey/util/tiktoken_.py
newssurvey/workflow/llm/accumulate_search_terms.py
newssurvey/workflow/llm/combine_articles.py
newssurvey/workflow/llm/condense_articles.py
newssurvey/workflow/llm/create_title.py
newssurvey/workflow/llm/filter_articles.py
newssurvey/workflow/llm/filter_search_results.py
newssurvey/workflow/llm/list_search_terms.py
newssurvey/workflow/llm/list_sections.py
newssurvey/workflow/llm/rate_articles.py
newssurvey/workflow/llm/refine_sections.py
newssurvey/workflow/source/get_articles.py
newssurvey/workflow/source/map_citations.py
newssurvey/workflow/user/output.py
newssurvey/workflow/user/query.py
newssurvey/workflow/user/source.py
newssurvey-0.11.0.dist-info/METADATA
newssurvey-0.11.0.dist-info/WHEEL
newssurvey-0.11.0.dist-info/entry_points.txt
newssurvey-0.11.0.dist-info/licenses/LICENSE
newssurvey-0.11.0.dist-info/RECORD
