Metadata-Version: 2.3
Name: newssurvey
Version: 0.11.0
Summary: Write a survey report using a supported news site and GPT-4 LLM 
Project-URL: Repository, https://github.com/impredicative/newssurvey
Author-email: Ouroboros Chrysopoeia <impredicative@users.noreply.github.com>
Keywords: GPT-4o,news,news-summarization
Classifier: Development Status :: 5 - Production/Stable
Classifier: License :: OSI Approved :: GNU Lesser General Public License v3 (LGPLv3)
Classifier: Natural Language :: English
Classifier: Programming Language :: Python :: 3.12
Classifier: Topic :: Internet :: WWW/HTTP :: Dynamic Content :: News/Diary
Classifier: Topic :: Scientific/Engineering :: Artificial Intelligence
Classifier: Topic :: Text Processing :: Linguistic
Requires-Python: >=3.12
Requires-Dist: click>=8.1.8
Requires-Dist: diskcache>=5.6.3
Requires-Dist: hext>=1.0.12
Requires-Dist: locket>=1.0.0
Requires-Dist: numpy>=2.2.3
Requires-Dist: openai>=1.64.0
Requires-Dist: pathvalidate>=3.2.3
Requires-Dist: python-dotenv>=1.0.1
Requires-Dist: reportlab>=4.3.1
Requires-Dist: requests>=2.32.3
Requires-Dist: scipy>=1.15.2
Requires-Dist: tiktoken>=0.9.0
